[{"slug":"SLIM","link":"https://secoli.com.br/brinde/Trio-de-Necessaires-KIT-4920-11009","img":"https://www.secoli.com.br/img/splash/NOVO-3.png","title":"Trio de Necessaires","cat_prod":"SLIM","sku":"KIT-4920"},{"slug":"SLIM","link":"https://secoli.com.br/brinde/Necessaire-NES-1906A-10841","img":"https://www.secoli.com.br/timthumb/timthumb.php?src=/img/produtos/1/Necessaire-10841-101600.jpg&w=300","title":"Necessaire","cat_prod":"SLIM","sku":"NES-1906A"},{"slug":"SLIM","link":"https://secoli.com.br/brinde/Necessaire-Pocket-NES-19101-10732","img":"https://www.secoli.com.br/timthumb/timthumb.php?src=/img/produtos/1/Necessaire-10732-083637.jpg&w=300","title":"Necessaire Pocket","cat_prod":"SLIM","sku":"NES-19101"},{"slug":"SLIM","link":"https://secoli.com.br/brinde/NECESSAIRE-BUCAL-NES-2001-10937","img":"https://www.secoli.com.br/img/splash/NOVO-3.png","title":"NECESSAIRE BUCAL ","cat_prod":"SLIM","sku":"NES-2001"},{"slug":"SLIM","link":"https://secoli.com.br/brinde/Necessaire-NES-505-10334","img":"https://www.secoli.com.br/timthumb/timthumb.php?src=/img/produtos/1/Necessaire-10334-100006.jpg&w=300","title":"Necessaire","cat_prod":"SLIM","sku":"NES-505"},{"slug":"SLIM","link":"https://secoli.com.br/brinde/Necessaire-Carteira-NES-854-9835","img":"https://www.secoli.com.br/timthumb/timthumb.php?src=/img/produtos/1/Necessaire-9835-100740.jpg&w=300","title":"Necessaire Carteira","cat_prod":"SLIM","sku":"NES-854"},{"slug":"SLIM","link":"https://secoli.com.br/brinde/Necessaire-Estojo-NES-867-9926","img":"https://www.secoli.com.br/timthumb/timthumb.php?src=/img/produtos/1/Necessaire-9926-104425.jpg&w=300","title":"Necessaire Estojo","cat_prod":"SLIM","sku":"NES-867"},{"slug":"SLIM","link":"https://secoli.com.br/brinde/Necessaire-NES-870-9929","img":"https://www.secoli.com.br/timthumb/timthumb.php?src=/img/produtos/1/Necessaire-9929-145401.jpg&w=300","title":"Necessaire","cat_prod":"SLIM","sku":"NES-870"},{"slug":"SLIM","link":"https://secoli.com.br/brinde/Necessaire-NES-875-9962","img":"https://www.secoli.com.br/timthumb/timthumb.php?src=/img/produtos/1/Necessaire-9962-134952.jpg&w=300","title":"Necessaire","cat_prod":"SLIM","sku":"NES-875"},{"slug":"SLIM","link":"https://secoli.com.br/brinde/Necessaire-Slim-NES-880-10748","img":"https://www.secoli.com.br/timthumb/timthumb.php?src=/img/produtos/1/Necessaire-10748-162456.jpg&w=300","title":"Necessaire Slim","cat_prod":"SLIM","sku":"NES-880"},{"slug":"SLIM","link":"https://secoli.com.br/brinde/Necessaire-Dobravel-NES-881-10755","img":"https://www.secoli.com.br/timthumb/timthumb.php?src=/img/produtos/1/Necessaire-Dobravel-10755-171838.jpg&w=300","title":"Necessaire Dobrável","cat_prod":"SLIM","sku":"NES-881"},{"slug":"SLIM","link":"https://secoli.com.br/brinde/Necessaire-NES-883-10752","img":"https://www.secoli.com.br/timthumb/timthumb.php?src=/img/produtos/1/Necessaire-10752-164303.jpg&w=300","title":"Necessaire","cat_prod":"SLIM","sku":"NES-883"}]